Metadata-Version: 2.1
Name: bobross
Version: 1.1
Summary: A collection of quotes from Bob Ross
License: MIT
License-File: LICENSE
